llm_greenpt.py
llm_greenpt-0.0.2.dist-info/licenses/LICENSE
llm_greenpt-0.0.2.dist-info/METADATA
llm_greenpt-0.0.2.dist-info/WHEEL
llm_greenpt-0.0.2.dist-info/entry_points.txt
llm_greenpt-0.0.2.dist-info/top_level.txt
llm_greenpt-0.0.2.dist-info/RECORD
