Metadata-Version: 2.4
Name: llm-greenpt
Version: 0.0.2
Summary: A plugin to add support for the GreenPT AI inference service to llm
Author: Chris Adams
License-Expression: Apache-2.0
Project-URL: Homepage, https://github.com/mrchrisadams/llm-greenpt
Project-URL: Changelog, https://github.com/mrchrisadams/llm-greenpt/releases
Project-URL: Issues, https://github.com/mrchrisadams/llm-greenpt/issues
Project-URL: CI, https://github.com/mrchrisadams/llm-greenpt/actions
Requires-Python: >=3.10
License-File: LICENSE
Requires-Dist: llm
Provides-Extra: test
Requires-Dist: pytest; extra == "test"
Dynamic: license-file
